dhunter/.dhunter
dhunter/__init__.py
dhunter/__main__.py
dhunter/app.py
dhunter/args.py
dhunter/cli.py
dhunter/config.py
dhunter/const.py
dhunter/db_base.py
dhunter/db_dirs.py
dhunter/deduper.py
dhunter/dir_hash.py
dhunter/file_hash.py
dhunter/file_hash_cache.py
dhunter/filter.py
dhunter/hash_base.py
dhunter/hash_manager.py
dhunter/log.py
dhunter/overrides_decorator.py
dhunter/util.py
dhunter/core/.dhunter
dhunter/core/__init__.py
dhunter/core/args_base.py
dhunter/core/config_base.py
dhunter/core/const.py
dhunter/core/db_base.py
dhunter/core/db_dirs.py
dhunter/core/dir_hash.py
dhunter/core/file_hash.py
dhunter/core/file_hash_cache.py
dhunter/core/filter.py
dhunter/core/hash_base.py
dhunter/core/hash_manager.py
dhunter/core/log.py
dhunter/hunter/.dhunter
dhunter/hunter/__init__.py
dhunter/hunter/args.py
dhunter/hunter/config.py
dhunter/hunter/hunter.py
dhunter/scanner/.dhunter
dhunter/scanner/__init__.py
dhunter/scanner/args.py
dhunter/scanner/config.py
dhunter/scanner/scanner.py
dhunter/util/.dhunter
dhunter/util/__init__.py
dhunter/util/overrides_decorator.py
dhunter/util/util.py
dhunter-1.3.0.dist-info/.dhunter
dhunter-1.3.0.dist-info/LICENSE
dhunter-1.3.0.dist-info/METADATA
dhunter-1.3.0.dist-info/WHEEL
dhunter-1.3.0.dist-info/entry_points.txt
dhunter-1.3.0.dist-info/top_level.txt
dhunter-1.3.0.dist-info/RECORD
