Metadata-Version: 2.1
Name: dhunter
Version: 1.3.0
Summary: The hunter - fast and easy file duplicate finder utility.
Home-page: https://github.com/MarcinOrlowski/dhunter
Author: Marcin Orlowski
Author-email: mail@marcinOrlowski.com
License: MIT License
Project-URL: Bug Tracker, https://github.com/MarcinOrlowski/dhunter/issues
Project-URL: Documentation, https://github.com/MarcinOrlowski/dhunter/
Project-URL: Source Code, https://github.com/MarcinOrlowski/dhunter/
Keywords: file duplicates deduplicate
Platform: UNKNOWN
Classifier: Programming Language :: Python :: 3
Classifier: License :: OSI Approved :: MIT License
Classifier: Operating System :: OS Independent
Requires-Python: >=3.6
Requires-Dist: argparse (>=1.4.0)
